Metadata-Version: 2.1
Name: sssss
Version: 0.1.1
Summary: Static (version of) Shamir's Secret Sharing Scheme
Home-page: https://github.com/reity/sssss
Author: Wyatt Howe
Author-email: whowe@bu.edu
License: CC0
Platform: UNKNOWN
